LICENSE
README.md
setup.cfg
setup.py
trace_feature/__init__.py
trace_feature/trace_feature.py
trace_feature.egg-info/PKG-INFO
trace_feature.egg-info/SOURCES.txt
trace_feature.egg-info/dependency_links.txt
trace_feature.egg-info/entry_points.txt
trace_feature.egg-info/requires.txt
trace_feature.egg-info/top_level.txt
trace_feature/core/__init__.py
trace_feature/core/base_config.py
trace_feature/core/base_execution.py
trace_feature/core/models.py
trace_feature/core/features/__init__.py
trace_feature/core/features/gherkin_parser.py
trace_feature/core/ruby/__init__.py
trace_feature/core/ruby/read_methods.py
trace_feature/core/ruby/ruby_config.py
trace_feature/core/ruby/ruby_execution.py
trace_feature/core/ruby/ruby_spec_execution.py
trace_feature/core/ruby/spec_models.py