Metadata-Version: 2.1
Name: trace-feature
Version: 1.0
Summary: A lib to trace bdd features.
Home-page: https://github.com/vitorbribas/trace_feature
Author: Rafael Fazzolino
Author-email: fazzolino29@gmail.com
License: MIT
Download-URL: https://github.com/vitorbribas/trace_feature/archive/refs/tags/v_1.tar.gz
Keywords: BDD,Trace
Platform: UNKNOWN
License-File: LICENSE
